soteria_sdk/__init__.py
soteria_sdk/client.py
soteria_sdk/decorators.py
soteria_sdk/exceptions.py
soteria_sdk-0.1.3.dist-info/WHEEL
soteria_sdk-0.1.3.dist-info/METADATA
soteria_sdk-0.1.3.dist-info/RECORD
