Metadata-Version: 2.3
Name: soteria-sdk
Version: 0.1.3
Summary: A lightweight SDK to use Soteria's firewall
License: MIT
Classifier: Programming Language :: Python :: 3
Classifier: License :: OSI Approved :: MIT License
Classifier: Operating System :: OS Independent
Requires-Dist: requests>=2.32.5
Requires-Python: >=3.11
